portable_ffmpeg/__init__.py
portable_ffmpeg/config.py
portable_ffmpeg/core.py
portable_ffmpeg/downloaders.py
portable_ffmpeg/enums.py
portable_ffmpeg/py.typed
portable_ffmpeg-0.1.0.dist-info/METADATA
portable_ffmpeg-0.1.0.dist-info/WHEEL
portable_ffmpeg-0.1.0.dist-info/entry_points.txt
portable_ffmpeg-0.1.0.dist-info/RECORD
