Metadata-Version: 2.4
Name: portable-ffmpeg
Version: 0.1.0
Summary: Downloads static ffmpeg builds for Windows, macOS, and Linux
Project-URL: Homepage, https://github.com/mrkbac/portable-ffmpeg
Project-URL: Repository, https://github.com/mrkbac/portable-ffmpeg
Project-URL: Issues, https://github.com/mrkbac/portable-ffmpeg/issues
Author-email: Marko Bausch <60338487+mrkbac@users.noreply.github.com>
License: MIT
Keywords: audio,ffmpeg,ffprobe,multimedia,portable,static,video
Classifier: Development Status :: 4 - Beta
Classifier: Intended Audience :: Developers
Classifier: License :: OSI Approved :: MIT License
Classifier: Operating System :: OS Independent
Classifier: Programming Language :: Python :: 3
Classifier: Programming Language :: Python :: 3.10
Classifier: Programming Language :: Python :: 3.11
Classifier: Programming Language :: Python :: 3.12
Classifier: Programming Language :: Python :: 3.13
Classifier: Topic :: Multimedia :: Sound/Audio
Classifier: Topic :: Multimedia :: Video
Classifier: Topic :: Software Development :: Libraries :: Python Modules
Requires-Python: >=3.10
Provides-Extra: dev
Requires-Dist: pre-commit; extra == 'dev'
Requires-Dist: pyright; extra == 'dev'
Requires-Dist: pytest-cov; extra == 'dev'
Requires-Dist: pytest>=8.4.0; extra == 'dev'
Requires-Dist: ruff; extra == 'dev'
